limecore/util/__init__.py
limecore/util/casing.py
limecore/util/typing.py
limecore_util-0.1.4.dist-info/LICENSE.txt
limecore_util-0.1.4.dist-info/METADATA
limecore_util-0.1.4.dist-info/WHEEL
limecore_util-0.1.4.dist-info/top_level.txt
limecore_util-0.1.4.dist-info/RECORD
