Metadata-Version: 2.1
Name: limecore-util
Version: 0.1.4
Summary: limecore: Utilities
Home-page: https://github.com/limecore/util
Author: Daniel Bradberry
Author-email: daniel@danielbradberry.com
License: MIT
Platform: UNKNOWN
Classifier: Programming Language :: Python :: 3
Classifier: License :: OSI Approved :: MIT License
Classifier: Operating System :: OS Independent
Requires-Python: >=3.6
